c7d/__init__.py
c7d/__main__.py
c7d/cli.py
c7d/core.py
c7d-0.1.0.dist-info/WHEEL
c7d-0.1.0.dist-info/entry_points.txt
c7d-0.1.0.dist-info/METADATA
c7d-0.1.0.dist-info/RECORD
