Metadata-Version: 2.3
Name: c7d
Version: 0.1.0
Summary: Tiny Cisco Type 7 (c7) encoder/decoder with a CLI.
Keywords: cisco,type7,password,decoder,encoder,security,networking
Author: Emil Bisgaard Commerou
License: MIT
Classifier: Development Status :: 4 - Beta
Classifier: Intended Audience :: Developers
Classifier: Intended Audience :: System Administrators
Classifier: License :: OSI Approved :: MIT License
Classifier: Programming Language :: Python
Classifier: Programming Language :: Python :: 3
Classifier: Programming Language :: Python :: 3 :: Only
Classifier: Programming Language :: Python :: 3.8
Classifier: Programming Language :: Python :: 3.9
Classifier: Programming Language :: Python :: 3.10
Classifier: Programming Language :: Python :: 3.11
Classifier: Programming Language :: Python :: 3.12
Classifier: Topic :: Security :: Cryptography
Classifier: Topic :: Utilities
Requires-Python: >=3.8
Project-URL: Homepage, https://example.com/c7d
Project-URL: Repository, https://example.com/c7d
